subconv/__init__.py
subconv/__main__.py
subconv/_decorators.py
subconv/_metaclasses.py
subconv/_version.py
subconv/parser.py
subconv/prompts.py
subconv/service.py
subconv/translator.py
subconv/core/models.py
subconv-1.1.2.dist-info/METADATA
subconv-1.1.2.dist-info/WHEEL
subconv-1.1.2.dist-info/entry_points.txt
subconv-1.1.2.dist-info/licenses/LICENSE
subconv-1.1.2.dist-info/RECORD
