Metadata-Version: 2.4
Name: subconv
Version: 1.1.2
Summary: Async SRT subtitle translator using OpenAI
Project-URL: Homepage, https://github.com/vnniciusg/subconv
Project-URL: Repository, https://github.com/vnniciusg/subconv
Project-URL: Issues, https://github.com/vnniciusg/subconv/issues
License-File: LICENSE
Requires-Python: >=3.13
Requires-Dist: click>=8.3.1
Requires-Dist: loguru>=0.7.3
Requires-Dist: openai>=2.15.0
Requires-Dist: python-dotenv>=1.2.1
Requires-Dist: tenacity>=9.1.2
